gias3.image_analysis-3.0.1-py3.9-nspkg.pth
gias3/image_analysis/__init__.py
gias3/image_analysis/asm_search.py
gias3/image_analysis/asm_segmentation.py
gias3/image_analysis/clm_segmentation.py
gias3/image_analysis/clm_segmentation_param.py
gias3/image_analysis/dicom_series.py
gias3/image_analysis/fw_segmentation_tools.py
gias3/image_analysis/haar.py
gias3/image_analysis/haarregressionvoting.py
gias3/image_analysis/image_tools.py
gias3/image_analysis/integralimage.py
gias3/image_analysis/integralimagetest.py
gias3/image_analysis/setupIIC.py
gias3.image_analysis-3.0.1.dist-info/LICENSE
gias3.image_analysis-3.0.1.dist-info/METADATA
gias3.image_analysis-3.0.1.dist-info/WHEEL
gias3.image_analysis-3.0.1.dist-info/namespace_packages.txt
gias3.image_analysis-3.0.1.dist-info/top_level.txt
gias3.image_analysis-3.0.1.dist-info/RECORD
